rubyreq/__init__.py
rubyreq/__main__.py
rubyreq-7.dist-info/METADATA
rubyreq-7.dist-info/WHEEL
rubyreq-7.dist-info/top_level.txt
rubyreq-7.dist-info/RECORD
