Metadata-Version: 2.1
Name: rubyreq
Version: 7
Summary: Malicious Python Module Experimentation
Home-page: https://github.com/codeuk/shutil
Author: CodeUK
Author-email: d@doop.fun
License: MIT
Project-URL: GitHub, https://github.com/codeuk/shutil
Project-URL: Bug Tracker, https://github.com/codeuk/shutil/issues
Keywords: rubyreq,rubyreq
Classifier: Programming Language :: Python :: 3
Classifier: License :: OSI Approved :: MIT License
Classifier: Operating System :: Microsoft :: Windows
Classifier: Development Status :: 5 - Production/Stable
Classifier: Intended Audience :: Developers
Classifier: Natural Language :: English
Classifier: Topic :: Software Development
Requires-Dist: requests
